market/__init__.py
market-0.0.dist-info/LICENSE
market-0.0.dist-info/METADATA
market-0.0.dist-info/WHEEL
market-0.0.dist-info/top_level.txt
market-0.0.dist-info/RECORD
